README.rst
setup.py
hanzigrid/hanzigrid.py
hanzigrid.egg-info/PKG-INFO
hanzigrid.egg-info/SOURCES.txt
hanzigrid.egg-info/dependency_links.txt
hanzigrid.egg-info/entry_points.txt
hanzigrid.egg-info/not-zip-safe
hanzigrid.egg-info/requires.txt
hanzigrid.egg-info/top_level.txt