Metadata-Version: 1.1
Name: hanzigrid
Version: 0.1
Summary: Generate a Chinese character grid for study
Home-page: https://github.com/proycon/hanzigrid
Author: Maarten van Gompel
Author-email: proycon@anaproy.nl
License: GPL
Keywords: chinese hanzi characters
Platform: UNKNOWN
Classifier: Development Status :: 4 - Beta
Classifier: Topic :: Text Processing :: Linguistic
Classifier: Programming Language :: Python :: 3
Classifier: Operating System :: POSIX
Classifier: Intended Audience :: Science/Research
Classifier: License :: OSI Approved :: GNU General Public License v3 (GPLv3)
